dummydb/__init__.py
dummydb/main.py
dummydb-0.1.6.dist-info/LICENSE
dummydb-0.1.6.dist-info/METADATA
dummydb-0.1.6.dist-info/WHEEL
dummydb-0.1.6.dist-info/top_level.txt
dummydb-0.1.6.dist-info/RECORD
