Metadata-Version: 2.1
Name: dummydb
Version: 0.1.6
Summary: A lightweight in-memory database for Python — perfect for testing and prototyping.
Home-page: https://github.com/vibhakar2007/dummydb
Author: Vibhakar S
Author-email: vibhakarsenth@gmail.com
License: MIT
Classifier: Programming Language :: Python :: 3
Classifier: License :: OSI Approved :: MIT License
Classifier: Operating System :: OS Independent
Requires-Python: >=3.7
License-File: LICENSE
